cmdline_add_args/__init__.py
cmdline_add_args/__main__.py
cmdline_add_args/allure_report_path.py
cmdline_add_args/plugin.py
pytest_cmdline_add_args-1.9.5.dist-info/METADATA
pytest_cmdline_add_args-1.9.5.dist-info/WHEEL
pytest_cmdline_add_args-1.9.5.dist-info/entry_points.txt
pytest_cmdline_add_args-1.9.5.dist-info/top_level.txt
pytest_cmdline_add_args-1.9.5.dist-info/RECORD
