Metadata-Version: 2.1
Name: pytest-cmdline-add-args
Version: 1.9.5
Summary: Pytest plugin for custom argument handling and Allure reporting. This plugin allows you to add arguments before running a test.
Author-email: Yevhen Halitsyn <galitsyn.evgeniy955@gmail.com>
License: MIT
